{
    "symbol": "4013",
    "name": "سليمان الحبيب",
    "name_en": "SULAIMAN ALHABIB",
    "price": 215.1,
    "change": 2.7,
    "change_percent": 1.27,
    "open": 212.5,
    "high": 215.1,
    "low": 211.5,
    "previous_close": 212.4,
    "volume": 83774,
    "value": 17928693.2,
    "bid": 214.4,
    "ask": 215.1,
    "bid_size": 1001,
    "ask_size": 2408,
    "liquidity": {
        "inflow_value": 10724652.53,
        "inflow_volume": 50070,
        "inflow_trades": 690,
        "outflow_value": 7204040.72,
        "outflow_volume": 33704,
        "outflow_trades": 787,
        "net_value": 3520611.8099999996
    },
    "updated_at": "2026-07-16T12:19:14+00:00",
    "is_delayed": true
}