{
    "address1": "Building Number 6575",
    "address2": "As-Safarat District",
    "city": "Riyadh",
    "zip": "12511",
    "country": "Saudi Arabia",
    "phone": "966 11 481 6666",
    "website": "https://www.taiba.com.sa",
    "industry": "Lodging",
    "industryKey": "lodging",
    "industryDisp": "Lodging",
    "sector": "Consumer Cyclical",
    "sectorKey": "consumer-cyclical",
    "sectorDisp": "Consumer Cyclical",
    "longBusinessSummary": "Taiba Investment Company invests in, buys, develops, sells, leases, operates, and manages real estate and hospitality projects in the Kingdom of Saudi Arabia. It operates through Real Estate, Tourism, and Property Management segments. The company leases residential and commercial centers, as well as offers property-level management and related services. It is also involved in the operation and accommodation of hotels, hotel apartments, serviced suites, and tourist resorts, as well as offers Hajj services. In addition, the company engages in the management and operations of hotels and other properties. Further, it buys, sells, leases, operates, and manages hospitals, recreational and other residential, and non-residential and tourism facilities. Additionally, the company enages in the development, construction, and maintenance of commercial, residential, and other real estate facilities; architectural, civil, mechanical, electrical, and agricultural contracting activities; and industrial and mining business, as well as offers credit and mortgage services. The company was formerly known as Taiba Holding Co. and changed its name to Taiba Investment Company in May 2019. Taiba Investment Company was founded in 1976 and is based in Riyadh, the Kingdom of Saudi Arabia.",
    "companyOfficers": [
        {
            "maxAge": 1,
            "name": "Mr. Sultan  bin Badr Al-Otaibi",
            "title": "Chief Executive Officer",
            "exercisedValue": 0,
            "unexercisedValue": 0
        },
        {
            "maxAge": 1,
            "name": "Mr. Amin Abdullah Albukhari",
            "title": "Chief Financial Officer",
            "exercisedValue": 0,
            "unexercisedValue": 0
        },
        {
            "maxAge": 1,
            "name": "Engineer Saleh  Bin Habdan Al-Habdan",
            "title": "MD & Director",
            "exercisedValue": 0,
            "unexercisedValue": 0
        }
    ],
    "executiveTeam": [],
    "maxAge": 86400,
    "priceHint": 2,
    "previousClose": 18.49,
    "open": 18.23,
    "dayLow": 18.23,
    "dayHigh": 18.52,
    "regularMarketPreviousClose": 18.49,
    "regularMarketOpen": 18.23,
    "regularMarketDayLow": 18.23,
    "regularMarketDayHigh": 18.52,
    "dividendRate": 0.34,
    "dividendYield": 1.83,
    "exDividendDate": 1778457600,
    "payoutRatio": 0.5435,
    "fiveYearAvgDividendYield": 7.12,
    "beta": 0.285,
    "trailingPE": 25.430553,
    "forwardPE": 12.046052,
    "volume": 100285,
    "regularMarketVolume": 100285,
    "averageVolume": 243068,
    "averageVolume10days": 139997,
    "averageDailyVolume10Day": 139997,
    "bid": 18.31,
    "ask": 18.38,
    "bidSize": 0,
    "askSize": 0,
    "marketCap": 9154999296,
    "nonDilutedMarketCap": 9245000000,
    "fiftyTwoWeekLow": 15.835807,
    "fiftyTwoWeekHigh": 22.65979,
    "allTimeHigh": 43.8,
    "allTimeLow": 7.292806,
    "priceToSalesTrailing12Months": 6.7102103,
    "fiftyDayAverage": 19.518818,
    "twoHundredDayAverage": 19.10052,
    "trailingAnnualDividendRate": 0.0,
    "trailingAnnualDividendYield": 0.0,
    "currency": "SAR",
    "tradeable": false,
    "enterpriseValue": 11294586880,
    "profitMargins": 0.26739,
    "floatShares": 274610126,
    "sharesOutstanding": 500000000,
    "heldPercentInsiders": 0.14363,
    "heldPercentInstitutions": 0.33843,
    "impliedSharesOutstanding": 500000000,
    "bookValue": 13.701,
    "priceToBook": 1.3363987,
    "lastFiscalYearEnd": 1767139200,
    "nextFiscalYearEnd": 1798675200,
    "mostRecentQuarter": 1767139200,
    "earningsQuarterlyGrowth": -0.268,
    "netIncomeToCommon": 364807968,
    "trailingEps": 0.72,
    "forwardEps": 1.52,
    "lastSplitFactor": "1.9197:1",
    "lastSplitDate": 1778457600,
    "enterpriseToRevenue": 8.278,
    "enterpriseToEbitda": 23.043,
    "52WeekChange": -0.115713656,
    "SandP52WeekChange": 0.20247209,
    "lastDividendValue": 0.338595,
    "lastDividendDate": 1778457600,
    "quoteType": "EQUITY",
    "currentPrice": 18.31,
    "targetHighPrice": 24.69135,
    "targetLowPrice": 24.69135,
    "targetMeanPrice": 24.69135,
    "targetMedianPrice": 24.69135,
    "recommendationMean": 1.0,
    "recommendationKey": "strong_buy",
    "numberOfAnalystOpinions": 1,
    "totalCash": 102585656,
    "totalCashPerShare": 0.205,
    "ebitda": 490146784,
    "totalDebt": 2164094464,
    "quickRatio": 0.231,
    "currentRatio": 0.314,
    "totalRevenue": 1364338688,
    "debtToEquity": 31.235,
    "revenuePerShare": 2.729,
    "returnOnAssets": 0.02125,
    "returnOnEquity": 0.05237,
    "grossProfits": 528286048,
    "freeCashflow": -341374432,
    "operatingCashflow": 465982848,
    "earningsGrowth": -0.268,
    "revenueGrowth": 0.068,
    "grossMargins": 0.38721,
    "ebitdaMargins": 0.35926,
    "operatingMargins": 0.09847,
    "financialCurrency": "SAR",
    "symbol": "4090.SR",
    "language": "en-US",
    "region": "US",
    "typeDisp": "Equity",
    "quoteSourceName": "Delayed Quote",
    "triggerable": false,
    "customPriceAlertConfidence": "LOW",
    "fiftyTwoWeekChangePercent": -11.571365,
    "earningsTimestampStart": 1754909940,
    "earningsTimestampEnd": 1755259200,
    "isEarningsDateEstimate": true,
    "epsTrailingTwelveMonths": 0.72,
    "epsForward": 1.52,
    "fiftyDayAverageChange": -1.2088184,
    "fiftyDayAverageChangePercent": -0.061930925,
    "twoHundredDayAverageChange": -0.7905197,
    "twoHundredDayAverageChangePercent": -0.041387342,
    "sourceInterval": 15,
    "exchangeDataDelayedBy": 15,
    "prevName": "Taiba Investments Co.",
    "nameChangeDate": "2026-07-16",
    "averageAnalystRating": "1.0 - Strong Buy",
    "cryptoTradeable": false,
    "marketState": "CLOSED",
    "shortName": "Taiba Investments Co.",
    "longName": "Taiba Investment Company",
    "regularMarketTime": 1784204353,
    "exchange": "SAU",
    "messageBoardId": "finmb_10361125",
    "exchangeTimezoneName": "Asia/Riyadh",
    "exchangeTimezoneShortName": "AST",
    "gmtOffSetMilliseconds": 10800000,
    "market": "sr_market",
    "esgPopulated": false,
    "hasPrePostMarketData": false,
    "firstTradeDateMilliseconds": 1267686000000,
    "regularMarketChange": -0.1800003,
    "regularMarketDayRange": "18.23 - 18.52",
    "fullExchangeName": "Saudi",
    "averageDailyVolume3Month": 243068,
    "fiftyTwoWeekLowChange": 2.4741926,
    "fiftyTwoWeekLowChangePercent": 0.15624039,
    "fiftyTwoWeekRange": "15.835807 - 22.65979",
    "fiftyTwoWeekHighChange": -4.3497906,
    "fiftyTwoWeekHighChangePercent": -0.19196077,
    "corporateActions": [],
    "regularMarketChangePercent": -0.97350085,
    "regularMarketPrice": 18.31,
    "trailingPegRatio": null
}