{
    "address1": "P.O. Box 10448",
    "city": "Riyadh",
    "zip": "11626",
    "country": "Saudi Arabia",
    "phone": "966 92 000 9016",
    "website": "https://alsaifgallery.com",
    "industry": "Furnishings, Fixtures & Appliances",
    "industryKey": "furnishings-fixtures-appliances",
    "industryDisp": "Furnishings, Fixtures & Appliances",
    "sector": "Consumer Cyclical",
    "sectorKey": "consumer-cyclical",
    "sectorDisp": "Consumer Cyclical",
    "longBusinessSummary": "Al-Saif Stores for Development & Investment Company engages in the wholesale and retail sale of household utensils, electrical appliances, and cleaning supplies in the Kingdom of Saudi Arabia. It offers kitchen appliances; home appliances; large appliances; coffee makers; built in appliances; televisions and accessories; thermoses; tea and coffee maker; serve ware; food containers; cookware; home products; health & beauty products; kitchen spare parts; and furniture; dough mixers; refrigerators and freezers; electric pots; and air fryers. The company also engages in the general contracting; construction, repair, restoration, and demolition of buildings; public construction of road works, water and sewage works, dams, drilling wells; maintenance and operation of electrical, mechanical, and electronic installation; landscaping and blacksmithing, carpentry, aluminum, decoration, gypsum, maintenance, and cleaning works; management and operation of cities, utilities, buildings, and public and private facilities; and buying and owning real estate and lands to construct buildings. It also sells its products online. Al-Saif Stores for Development & Investment Company was founded in 2014 in and is headquartered in Riyadh, the Kingdom of Saudi Arabia.",
    "fullTimeEmployees": 1198,
    "companyOfficers": [
        {
            "maxAge": 1,
            "name": "Ahmed bin Saleh bin Muhammad Al-Sultan",
            "age": 38,
            "title": "CEO & Executive Director",
            "yearBorn": 1987,
            "exercisedValue": 0,
            "unexercisedValue": 0
        },
        {
            "maxAge": 1,
            "name": "Motaz  Al Ashqar",
            "title": "Chief Financial Officer",
            "exercisedValue": 0,
            "unexercisedValue": 0
        },
        {
            "maxAge": 1,
            "name": "Muhammad Ahmed Muhammad Al-Nawaji",
            "age": 41,
            "title": "Sales & Operations Manager",
            "yearBorn": 1984,
            "exercisedValue": 0,
            "unexercisedValue": 0
        },
        {
            "maxAge": 1,
            "name": "Mr. Faisal bin Saif bin Muaid Al-Sultan",
            "age": 31,
            "title": "Secretary of the Board and Legal Affairs & Governance Officer",
            "yearBorn": 1994,
            "exercisedValue": 0,
            "unexercisedValue": 0
        },
        {
            "maxAge": 1,
            "name": "Haitham bin Suleiman bin Muhammad Alsaif",
            "age": 38,
            "title": "Marketing & Business Development Manager & Non-Executive Director",
            "yearBorn": 1987,
            "exercisedValue": 0,
            "unexercisedValue": 0
        },
        {
            "maxAge": 1,
            "name": "Muhammad bin Suleiman bin Muhammad Alsaif",
            "age": 39,
            "title": "MD & Executive Non-Independent Director",
            "yearBorn": 1986,
            "exercisedValue": 0,
            "unexercisedValue": 0
        }
    ],
    "executiveTeam": [],
    "maxAge": 86400,
    "priceHint": 2,
    "previousClose": 6.65,
    "open": 6.65,
    "dayLow": 6.64,
    "dayHigh": 6.7,
    "regularMarketPreviousClose": 6.65,
    "regularMarketOpen": 6.65,
    "regularMarketDayLow": 6.64,
    "regularMarketDayHigh": 6.7,
    "dividendRate": 0.06,
    "dividendYield": 0.9,
    "exDividendDate": 1777248000,
    "payoutRatio": 0.0,
    "beta": 0.163,
    "trailingPE": 37.22222,
    "volume": 57222,
    "regularMarketVolume": 57222,
    "averageVolume": 191957,
    "averageVolume10days": 73024,
    "averageDailyVolume10Day": 73024,
    "bid": 6.69,
    "ask": 6.7,
    "marketCap": 2344999936,
    "nonDilutedMarketCap": 2327500000,
    "fiftyTwoWeekLow": 6.11,
    "fiftyTwoWeekHigh": 7.21,
    "allTimeHigh": 12.1,
    "allTimeLow": 6.11,
    "priceToSalesTrailing12Months": 2.9211025,
    "fiftyDayAverage": 6.8794,
    "twoHundredDayAverage": 6.60655,
    "trailingAnnualDividendRate": 0.06,
    "trailingAnnualDividendYield": 0.009022556,
    "currency": "SAR",
    "tradeable": false,
    "enterpriseValue": 2472428800,
    "profitMargins": 0.076230004,
    "floatShares": 115090500,
    "sharesOutstanding": 350000000,
    "heldPercentInsiders": 0.625,
    "heldPercentInstitutions": 0.0036000002,
    "impliedSharesOutstanding": 350000000,
    "bookValue": 1.528,
    "priceToBook": 4.3848166,
    "lastFiscalYearEnd": 1767139200,
    "nextFiscalYearEnd": 1798675200,
    "mostRecentQuarter": 1774915200,
    "earningsQuarterlyGrowth": 0.09,
    "netIncomeToCommon": 61196684,
    "trailingEps": 0.18,
    "lastSplitFactor": "10:1",
    "lastSplitDate": 1688342400,
    "enterpriseToRevenue": 3.08,
    "enterpriseToEbitda": 26.367,
    "52WeekChange": -0.05807364,
    "SandP52WeekChange": 0.20247209,
    "lastDividendValue": 0.06,
    "lastDividendDate": 1777248000,
    "quoteType": "EQUITY",
    "currentPrice": 6.7,
    "targetHighPrice": 7.5,
    "targetLowPrice": 6.86,
    "targetMeanPrice": 7.18,
    "targetMedianPrice": 7.18,
    "recommendationMean": 3.0,
    "recommendationKey": "hold",
    "numberOfAnalystOpinions": 2,
    "totalCash": 100250800,
    "totalCashPerShare": 0.286,
    "ebitda": 93770848,
    "totalDebt": 227679696,
    "quickRatio": 0.989,
    "currentRatio": 4.386,
    "totalRevenue": 802779072,
    "debtToEquity": 42.575,
    "revenuePerShare": 2.294,
    "returnOnAssets": 0.05617,
    "returnOnEquity": 0.12128,
    "grossProfits": 181431344,
    "freeCashflow": 112486272,
    "operatingCashflow": 152867280,
    "earningsGrowth": 0.09,
    "revenueGrowth": 0.192,
    "grossMargins": 0.22600001,
    "ebitdaMargins": 0.116809994,
    "operatingMargins": 0.14771,
    "financialCurrency": "SAR",
    "symbol": "4192.SR",
    "language": "en-US",
    "region": "US",
    "typeDisp": "Equity",
    "quoteSourceName": "Delayed Quote",
    "triggerable": false,
    "customPriceAlertConfidence": "LOW",
    "hasPrePostMarketData": false,
    "firstTradeDateMilliseconds": 1672297200000,
    "regularMarketChange": 0.049999714,
    "regularMarketDayRange": "6.64 - 6.7",
    "fullExchangeName": "Saudi",
    "averageDailyVolume3Month": 191957,
    "fiftyTwoWeekLowChange": 0.5899997,
    "fiftyTwoWeekLowChangePercent": 0.09656296,
    "fiftyTwoWeekRange": "6.11 - 7.21",
    "fiftyTwoWeekHighChange": -0.5100002,
    "fiftyTwoWeekHighChangePercent": -0.07073512,
    "fiftyTwoWeekChangePercent": -5.807364,
    "epsTrailingTwelveMonths": 0.18,
    "fiftyDayAverageChange": -0.17939997,
    "fiftyDayAverageChangePercent": -0.026077852,
    "twoHundredDayAverageChange": 0.09344959,
    "twoHundredDayAverageChangePercent": 0.014144991,
    "marketState": "CLOSED",
    "corporateActions": [],
    "regularMarketTime": 1784203807,
    "exchange": "SAU",
    "messageBoardId": "finmb_1802524336",
    "exchangeTimezoneName": "Asia/Riyadh",
    "exchangeTimezoneShortName": "AST",
    "gmtOffSetMilliseconds": 10800000,
    "market": "sr_market",
    "esgPopulated": false,
    "regularMarketChangePercent": 0.7518754,
    "regularMarketPrice": 6.7,
    "shortName": "AlSaif Stores for Development a",
    "longName": "Al-Saif Stores for Development & Investment Company",
    "sourceInterval": 15,
    "exchangeDataDelayedBy": 15,
    "averageAnalystRating": "3.0 - Hold",
    "cryptoTradeable": false,
    "trailingPegRatio": null
}