{
    "address1": "Al Moroug District",
    "address2": "PO Box 86958",
    "city": "Riyadh",
    "zip": "11632",
    "country": "Saudi Arabia",
    "phone": "966 114509767",
    "fax": "966 114501824",
    "website": "https://www.herfy.com",
    "industry": "Restaurants",
    "industryKey": "restaurants",
    "industryDisp": "Restaurants",
    "sector": "Consumer Cyclical",
    "sectorKey": "consumer-cyclical",
    "sectorDisp": "Consumer Cyclical",
    "longBusinessSummary": "Herfy Food Services Company establishes and operates restaurants in the Kingdom of Saudi Arabia and internationally. The company operates through Restaurants, Meat Factory, and Bakeries. It operates restaurants under the HERFY name. The company also produces and sells frozen products, bakery and pastry products through bakeries and bakery shops under the Herfy Bakeries/Dokka name; and meat products. In addition, it provides cooked meals; catering services; purchases and sells land for constructing buildings; and owns, uses, maintains, and leases warehouses and food store fridges. Herfy Food Services Company was incorporated in 1981 and is headquartered in Riyadh, the Kingdom of Saudi Arabia.",
    "fullTimeEmployees": 4355,
    "companyOfficers": [
        {
            "maxAge": 1,
            "name": "Mr. Mohammad Lotfy Saleh Al Bargothy",
            "title": "Chief Executive Officer",
            "exercisedValue": 0,
            "unexercisedValue": 0
        },
        {
            "maxAge": 1,
            "name": "Mr. Saleh  Bin Abdulrahman Saleh Al Fadel",
            "age": 39,
            "title": "CFO & Administrative Officer",
            "yearBorn": 1986,
            "exercisedValue": 0,
            "unexercisedValue": 0
        },
        {
            "maxAge": 1,
            "name": "Mr. Saleh Muqbel Alkhalaf",
            "title": "Member of Audit Committee",
            "exercisedValue": 0,
            "unexercisedValue": 0
        }
    ],
    "executiveTeam": [],
    "maxAge": 86400,
    "priceHint": 2,
    "previousClose": 13.75,
    "open": 13.75,
    "dayLow": 13.6,
    "dayHigh": 13.94,
    "regularMarketPreviousClose": 13.75,
    "regularMarketOpen": 13.75,
    "regularMarketDayLow": 13.6,
    "regularMarketDayHigh": 13.94,
    "exDividendDate": 1683590400,
    "payoutRatio": 0.0,
    "fiveYearAvgDividendYield": 3.47,
    "beta": 0.252,
    "forwardPE": 36.68421,
    "volume": 36732,
    "regularMarketVolume": 36732,
    "averageVolume": 155785,
    "averageVolume10days": 105510,
    "averageDailyVolume10Day": 105510,
    "bid": 13.8,
    "ask": 13.57,
    "bidSize": 0,
    "askSize": 0,
    "marketCap": 901639168,
    "nonDilutedMarketCap": 889350000,
    "fiftyTwoWeekLow": 12.9,
    "fiftyTwoWeekHigh": 26.36,
    "allTimeHigh": 119.0,
    "allTimeLow": 12.9,
    "priceToSalesTrailing12Months": 0.8472848,
    "fiftyDayAverage": 14.8834,
    "twoHundredDayAverage": 15.97985,
    "trailingAnnualDividendRate": 0.0,
    "trailingAnnualDividendYield": 0.0,
    "currency": "SAR",
    "tradeable": false,
    "enterpriseValue": 1335091200,
    "profitMargins": -0.059,
    "floatShares": 23088173,
    "sharesOutstanding": 64680000,
    "heldPercentInsiders": 0.643,
    "heldPercentInstitutions": 0.0077,
    "impliedSharesOutstanding": 64680000,
    "bookValue": 13.069,
    "priceToBook": 1.0666462,
    "lastFiscalYearEnd": 1767139200,
    "nextFiscalYearEnd": 1798675200,
    "mostRecentQuarter": 1774915200,
    "netIncomeToCommon": -62789292,
    "trailingEps": -0.97,
    "forwardEps": 0.38,
    "lastSplitFactor": "7:5",
    "lastSplitDate": 1495497600,
    "enterpriseToRevenue": 1.255,
    "enterpriseToEbitda": 15.413,
    "52WeekChange": -0.40217394,
    "SandP52WeekChange": 0.20247209,
    "lastDividendValue": 0.5,
    "lastDividendDate": 1683590400,
    "quoteType": "EQUITY",
    "currentPrice": 13.94,
    "targetHighPrice": 20.1,
    "targetLowPrice": 13.5,
    "targetMeanPrice": 17.53333,
    "targetMedianPrice": 19.0,
    "recommendationMean": 4.33333,
    "recommendationKey": "underperform",
    "numberOfAnalystOpinions": 3,
    "totalCash": 14309807,
    "totalCashPerShare": 0.221,
    "ebitda": 86622856,
    "totalDebt": 447761824,
    "quickRatio": 0.518,
    "currentRatio": 1.226,
    "totalRevenue": 1064151232,
    "debtToEquity": 52.97,
    "revenuePerShare": 16.453,
    "returnOnAssets": 0.00247,
    "returnOnEquity": -0.07169,
    "grossProfits": 263868416,
    "freeCashflow": 94415632,
    "operatingCashflow": 120912088,
    "revenueGrowth": -0.069,
    "grossMargins": 0.24796,
    "ebitdaMargins": 0.08140001,
    "operatingMargins": 0.01612,
    "financialCurrency": "SAR",
    "symbol": "6002.SR",
    "language": "en-US",
    "region": "US",
    "typeDisp": "Equity",
    "quoteSourceName": "Delayed Quote",
    "triggerable": false,
    "customPriceAlertConfidence": "LOW",
    "regularMarketChangePercent": 1.3818151,
    "regularMarketPrice": 13.94,
    "corporateActions": [],
    "regularMarketTime": 1784203990,
    "exchange": "SAU",
    "messageBoardId": "finmb_5773576",
    "exchangeTimezoneName": "Asia/Riyadh",
    "exchangeTimezoneShortName": "AST",
    "gmtOffSetMilliseconds": 10800000,
    "market": "sr_market",
    "esgPopulated": false,
    "earningsTimestampStart": 1754305140,
    "earningsTimestampEnd": 1754654400,
    "isEarningsDateEstimate": true,
    "epsTrailingTwelveMonths": -0.97,
    "epsForward": 0.38,
    "epsCurrentYear": -0.21333,
    "priceEpsCurrentYear": -65.34477,
    "fiftyDayAverageChange": -0.9434004,
    "fiftyDayAverageChangePercent": -0.06338608,
    "twoHundredDayAverageChange": -2.0398502,
    "twoHundredDayAverageChangePercent": -0.12765141,
    "sourceInterval": 15,
    "exchangeDataDelayedBy": 15,
    "averageAnalystRating": "4.3 - Underperform",
    "cryptoTradeable": false,
    "shortName": "Herfy Food Services Co.",
    "longName": "Herfy Food Services Company",
    "hasPrePostMarketData": false,
    "firstTradeDateMilliseconds": 1267599600000,
    "regularMarketChange": 0.18999958,
    "regularMarketDayRange": "13.6 - 13.94",
    "fullExchangeName": "Saudi",
    "averageDailyVolume3Month": 155785,
    "fiftyTwoWeekLowChange": 1.04,
    "fiftyTwoWeekLowChangePercent": 0.080620155,
    "fiftyTwoWeekRange": "12.9 - 26.36",
    "fiftyTwoWeekHighChange": -12.420001,
    "fiftyTwoWeekHighChangePercent": -0.47116846,
    "fiftyTwoWeekChangePercent": -40.217392,
    "marketState": "CLOSED",
    "trailingPegRatio": null
}