{
    "address1": "3528 King Abdullah Bin Abdulaziz Road",
    "address2": "Unit No. 25 Al Nuzha District",
    "city": "Riyadh",
    "zip": "12471–6378",
    "country": "Saudi Arabia",
    "phone": "966 11 273 1400",
    "website": "https://www.gig.sa",
    "industry": "Insurance - Diversified",
    "industryKey": "insurance-diversified",
    "industryDisp": "Insurance - Diversified",
    "sector": "Financial Services",
    "sectorKey": "financial-services",
    "sectorDisp": "Financial Services",
    "longBusinessSummary": "Gulf Insurance Group provides insurance and reinsurance products and services for corporates, SMEs, and individual customers in the Kingdom of Saudi Arabia. It operates through Motor, Property and Casualty, Health, and Protection segments. The company offers car, travel, home, and motorcycle insurance products for individuals. It also provides group healthcare, life, business travel, group personal accident, business secure, motor fleet, marine, liability, property, and engineering insurance products for businesses. The company was formerly known as AXA Cooperative Insurance Company and changed its name to Gulf Insurance Group in June 2022. The company was founded in 2008 and is headquartered in Riyadh, the Kingdom of Saudi Arabia. Gulf Insurance Group is a subsidiary of Gulf Insurance Group (Gulf) B.S.C.",
    "companyOfficers": [
        {
            "maxAge": 1,
            "name": "Mr. Osama Kamel Mostafa Aly Kishk",
            "title": "Group Chief Financial Officer",
            "fiscalYear": 2023,
            "totalPay": 170500,
            "exercisedValue": 0,
            "unexercisedValue": 0
        },
        {
            "maxAge": 1,
            "name": "Mr. Farid Joseph Saber",
            "title": "Group Chief Operations Officer",
            "fiscalYear": 2023,
            "totalPay": 181000,
            "exercisedValue": 0,
            "unexercisedValue": 0
        },
        {
            "maxAge": 1,
            "name": "Mr. Khaled Saoud Abdul Aziz Al Hasan",
            "age": 72,
            "title": "Vice Chairman & Group CEO",
            "yearBorn": 1953,
            "fiscalYear": 2023,
            "exercisedValue": 0,
            "unexercisedValue": 0
        },
        {
            "maxAge": 1,
            "name": "Mr. Khaled M. Al Sanousi",
            "title": "Group Executive Manager of Corporate Communications, Marketing/PR, IR & Admin Affairs Department",
            "fiscalYear": 2023,
            "exercisedValue": 0,
            "unexercisedValue": 0
        },
        {
            "maxAge": 1,
            "name": "Mr. Zohair  Safwani",
            "title": "Financial Controller",
            "fiscalYear": 2023,
            "exercisedValue": 0,
            "unexercisedValue": 0
        },
        {
            "maxAge": 1,
            "name": "Mr. Rami Selim El Baraki",
            "title": "Board Secretary",
            "fiscalYear": 2023,
            "exercisedValue": 0,
            "unexercisedValue": 0
        },
        {
            "maxAge": 1,
            "name": "Mr. Ahmed Galal Ragab",
            "title": "Chief Actuarial Officer, Head of Actuarial Operations & Group Actuarial",
            "fiscalYear": 2023,
            "exercisedValue": 0,
            "unexercisedValue": 0
        }
    ],
    "compensationAsOfEpochDate": 1703980800,
    "executiveTeam": [],
    "maxAge": 86400,
    "priceHint": 2,
    "previousClose": 31.24,
    "open": 31.5,
    "dayLow": 30.76,
    "dayHigh": 31.5,
    "regularMarketPreviousClose": 31.24,
    "regularMarketOpen": 31.5,
    "regularMarketDayLow": 30.76,
    "regularMarketDayHigh": 31.5,
    "dividendRate": 1.2,
    "dividendYield": 3.84,
    "exDividendDate": 1778976000,
    "payoutRatio": 0.4428,
    "beta": 0.294,
    "trailingPE": 11.3505535,
    "forwardPE": 13.1453,
    "volume": 66027,
    "regularMarketVolume": 66027,
    "averageVolume": 189792,
    "averageVolume10days": 68209,
    "averageDailyVolume10Day": 68209,
    "bid": 30.96,
    "ask": 28.14,
    "bidSize": 0,
    "askSize": 0,
    "marketCap": 1614899968,
    "nonDilutedMarketCap": 1640100000,
    "fiftyTwoWeekLow": 20.84,
    "fiftyTwoWeekHigh": 32.86,
    "allTimeHigh": 63.25,
    "allTimeLow": 6.889752,
    "priceToSalesTrailing12Months": 0.9563351,
    "fiftyDayAverage": 29.6972,
    "twoHundredDayAverage": 25.2772,
    "trailingAnnualDividendRate": 1.2,
    "trailingAnnualDividendYield": 0.038412295,
    "currency": "SAR",
    "tradeable": false,
    "enterpriseValue": 1088374016,
    "profitMargins": 0.084589995,
    "floatShares": 26250000,
    "sharesOutstanding": 52500000,
    "heldPercentInsiders": 0.0,
    "heldPercentInstitutions": 0.51959,
    "impliedSharesOutstanding": 52500000,
    "bookValue": 23.374,
    "priceToBook": 1.3159921,
    "lastFiscalYearEnd": 1767139200,
    "nextFiscalYearEnd": 1798675200,
    "mostRecentQuarter": 1774915200,
    "earningsQuarterlyGrowth": 0.615,
    "netIncomeToCommon": 142836992,
    "trailingEps": 2.71,
    "forwardEps": 2.34,
    "lastSplitFactor": "21:20",
    "lastSplitDate": 1700352000,
    "enterpriseToRevenue": 0.645,
    "enterpriseToEbitda": 5.388,
    "52WeekChange": 0.19054878,
    "SandP52WeekChange": 0.20247209,
    "lastDividendValue": 1.2,
    "lastDividendDate": 1778976000,
    "quoteType": "EQUITY",
    "currentPrice": 30.76,
    "recommendationKey": "none",
    "totalCash": 550121024,
    "totalCashPerShare": 10.478,
    "ebitda": 202003008,
    "totalDebt": 23595000,
    "quickRatio": 2.569,
    "currentRatio": 4.732,
    "totalRevenue": 1688633984,
    "debtToEquity": 1.923,
    "revenuePerShare": 32.164,
    "returnOnAssets": 0.04259,
    "returnOnEquity": 0.12038,
    "grossProfits": 236648992,
    "freeCashflow": -88249624,
    "operatingCashflow": 185688000,
    "earningsGrowth": 0.615,
    "revenueGrowth": 0.228,
    "grossMargins": 0.14014,
    "ebitdaMargins": 0.11963,
    "operatingMargins": 0.11582,
    "financialCurrency": "SAR",
    "symbol": "8250.SR",
    "language": "en-US",
    "region": "US",
    "typeDisp": "Equity",
    "quoteSourceName": "Delayed Quote",
    "triggerable": false,
    "customPriceAlertConfidence": "LOW",
    "fiftyDayAverageChange": 1.0627995,
    "fiftyDayAverageChangePercent": 0.035787866,
    "twoHundredDayAverageChange": 5.4827995,
    "twoHundredDayAverageChangePercent": 0.2169069,
    "sourceInterval": 15,
    "exchangeDataDelayedBy": 15,
    "prevName": "AXA Cooperative Insurance Co.",
    "nameChangeDate": "2026-07-16",
    "cryptoTradeable": false,
    "hasPrePostMarketData": false,
    "firstTradeDateMilliseconds": 1267686000000,
    "regularMarketChange": -0.47999954,
    "regularMarketDayRange": "30.76 - 31.5",
    "fullExchangeName": "Saudi",
    "averageDailyVolume3Month": 189792,
    "fiftyTwoWeekLowChange": 9.92,
    "fiftyTwoWeekLowChangePercent": 0.47600767,
    "fiftyTwoWeekRange": "20.84 - 32.86",
    "fiftyTwoWeekHighChange": -2.1000004,
    "fiftyTwoWeekHighChangePercent": -0.0639075,
    "fiftyTwoWeekChangePercent": 19.054878,
    "earningsTimestampStart": 1604573940,
    "earningsTimestampEnd": 1604573940,
    "epsTrailingTwelveMonths": 2.71,
    "epsForward": 2.34,
    "corporateActions": [],
    "regularMarketTime": 1784203808,
    "exchange": "SAU",
    "messageBoardId": "finmb_53474451",
    "exchangeTimezoneName": "Asia/Riyadh",
    "exchangeTimezoneShortName": "AST",
    "gmtOffSetMilliseconds": 10800000,
    "market": "sr_market",
    "esgPopulated": false,
    "regularMarketChangePercent": -1.5364902,
    "regularMarketPrice": 30.76,
    "shortName": "Gulf Insurance Group",
    "longName": "Gulf Insurance Group",
    "marketState": "CLOSED",
    "trailingPegRatio": null
}